{
    "version": "https://jsonfeed.org/version/1",
    "title": "1 Series Guides",
    "description": "",
    "home_page_url": "https://willjjones.github.io",
    "feed_url": "https://willjjones.github.io/feed.json",
    "user_comment": "",
    "author": {
        "name": "Will"
    },
    "items": [
        {
            "id": "https://willjjones.github.io/this-is-my-first-post.html",
            "url": "https://willjjones.github.io/this-is-my-first-post.html",
            "title": "This is my first post",
            "summary": "This is a post, lets see what it looks like when it spublished on my big boy. This is a happy message.",
            "content_html": "<p>This is a post, lets see what it looks like when it spublished on my big boy. </p>\n<p> </p>\n<p class=\"msg msg--success\">This is a happy message.</p>",
            "author": {
                "name": "Will"
            },
            "tags": [
            ],
            "date_published": "2019-08-24T23:41:05+01:00",
            "date_modified": "2019-08-24T23:41:05+01:00"
        }
    ]
}
